datacx/__init__.py
datacx/core.py
datacx/exceptions.py
datacx/databases/__init__.py
datacx/databases/database.py
datacx/datalakes/__init__.py
datacx/datalakes/datalake.py
datacx/datalakes/utils.py
datacx/datawarehouses/__init__.py
datacx/datawarehouses/datawarehouse.py
datacx/datawarehouses/utils.py
datacx/nosql/__init__.py
datacx/nosql/nosql.py
datacx-0.4.0.dist-info/LICENSE
datacx-0.4.0.dist-info/METADATA
datacx-0.4.0.dist-info/WHEEL
datacx-0.4.0.dist-info/top_level.txt
datacx-0.4.0.dist-info/RECORD
