Metadata-Version: 2.1
Name: datacx
Version: 0.4.0
Summary: Data Connectors for all data sources
Author-email: Vinish M <vinishuchiha@gmail.com>
License: MIT License
Project-URL: Homepage, https://github.com/VinishUchiha/datacx
Keywords: connectors,datalake reader,datawarehouse reader,dataconnector
Classifier: License :: OSI Approved :: MIT License
Classifier: Programming Language :: Python
Classifier: Programming Language :: Python :: 3
Requires-Python: >=3.7
License-File: LICENSE
Requires-Dist: boto3 (>=1.26.93)
Requires-Dist: google-cloud-storage (>=2.7.0)
Requires-Dist: azure-storage-blob (>=12.15.0)
Requires-Dist: pandas (>=1.0.0)
Requires-Dist: PyYAML
Requires-Dist: connectorx
Requires-Dist: snowflake-connector-python[pandas]
Requires-Dist: mysql-connector-python-rf
Requires-Dist: elasticsearch (>8.0.0)
Requires-Dist: sqlalchemy (==1.4.46)
Requires-Dist: pymongo
Requires-Dist: fastparquet
Requires-Dist: openpyxl
Requires-Dist: xlrd
Requires-Dist: xlwt
Requires-Dist: tomli ; python_version < "3.11"
Provides-Extra: dev
Requires-Dist: black ; extra == 'dev'
Requires-Dist: bumpver ; extra == 'dev'
Requires-Dist: isort ; extra == 'dev'
Requires-Dist: pip-tools ; extra == 'dev'
Requires-Dist: pytest ; extra == 'dev'
